coghotswap/__init__.py
coghotswap/__version__.py
coghotswap/coghotswap.py
coghotswap-0.0.2.dist-info/LICENSE
coghotswap-0.0.2.dist-info/METADATA
coghotswap-0.0.2.dist-info/WHEEL
coghotswap-0.0.2.dist-info/top_level.txt
coghotswap-0.0.2.dist-info/RECORD
