Metadata-Version: 2.1
Name: coghotswap
Version: 0.0.2
Summary: Allow hot reloading of extensions for Pycord a fork of discord.py
Home-page: https://github.com/TropicalShadow/coghotswap
Author: TropicalShadow
Author-email: me@tesseract.club
License: The MIT License (MIT)
Keywords: discord development hotswap
Classifier: Development Status :: 4 - Beta
Classifier: Intended Audience :: Developers
Classifier: Programming Language :: Python :: 3.7
Requires-Python: >=3.7
License-File: LICENSE
Requires-Dist: watchgod
